{
  "errata_id": "580c9bd7e05306645d8bd57c567a124a84b1f64d748bf5960a2307b9c6c8253c",
  "attachments": [],
  "tags": [
    "book:stax-phi",
    "assignment-type:homework",
    "context-cnxmod:a698e866-5321-4c57-8a1e-cc9f6255cf77",
    "lo:stax-phi:10-1-2",
    "book-slug:introduction-philosophy",
    "module-slug:introduction-philosophy:10-1-the-challenge-of-bioethics"
  ],
  "books": [
    {
      "name": "stax-phi",
      "lo": [
        "10-1-2"
      ]
    }
  ],
  "context": [
    "m00059"
  ]
}